pictures.py
setup.py
AIpictures.egg-info/PKG-INFO
AIpictures.egg-info/SOURCES.txt
AIpictures.egg-info/dependency_links.txt
AIpictures.egg-info/entry_points.txt
AIpictures.egg-info/requires.txt
AIpictures.egg-info/top_level.txt