Metadata-Version: 2.1
Name: AIpictures
Version: 1.0.2
Summary: My awesome package
Author: Justin Alter
Author-email: jane@example.com
